soupspoon/HtmlFile.py
soupspoon/Spoon.py
soupspoon/__init__.py
soupspoon/clean_html_text.py
soupspoon/clean_name.py
soupspoon/clone_beautiful_soup_tag.py
soupspoon/exceptions.py
soupspoon/find_all.py
soupspoon/find_between.py
soupspoon/find_links.py
soupspoon/flatten_dictionaries_and_lists.py
soupspoon/get_lists.py
soupspoon/get_same_type_siblings.py
soupspoon/get_table_shape.py
soupspoon/get_text.py
soupspoon/get_url_and_get_anchor.py
soupspoon/read_table.py
soupspoon/separate_row_header.py
soupspoon/htmltext/BaseHtmlText.py
soupspoon/htmltext/HtmlText.py
soupspoon/htmltext/Section.py
soupspoon/htmltext/StructuredText.py
soupspoon/htmltext/__init__.py
soupspoon/htmltext/get_children.py
soupspoon/htmltext/get_font_size.py
soupspoon/htmltext/get_raw_text.py
soupspoon/htmltext/get_text.py
soupspoon/htmltext/is_body_text.py
soupspoon/htmltext/is_break.py
soupspoon/htmltext/is_bullet_point.py
soupspoon/string/__init__.py
soupspoon/string/ends_with_punctuation.py
soupspoon/string/get_alphabetic.py
soupspoon/string/get_alphabetic_ratio.py
soupspoon/string/get_numeric_ratio.py
soupspoon/string/get_words.py
soupspoon/string/is_capitalized.py
soupspoon/string/is_short_text.py
soupspoon/string/strip_non_alphanumeric_from_beginning.py
soupspoon/text/__init__.py
soupspoon/text/get_html_text.py
soupspoon/text/get_style.py
soupspoon/text/get_text_and_depth.py
soupspoon-2022.4.20.dist-info/LICENSE
soupspoon-2022.4.20.dist-info/METADATA
soupspoon-2022.4.20.dist-info/WHEEL
soupspoon-2022.4.20.dist-info/top_level.txt
soupspoon-2022.4.20.dist-info/RECORD
