Metadata-Version: 2.1
Name: soupspoon
Version: 2022.4.20
Summary: Additional functionality for BeautifulSoup
Home-page: https://github.com/idin/soupspoon
Author: Idin
Author-email: py@idin.ca
License: MIT
Platform: UNKNOWN
Classifier: Development Status :: 3 - Alpha
Classifier: Intended Audience :: Developers
Classifier: Programming Language :: Python :: 3 :: Only
Classifier: Programming Language :: Python :: 3.6
Classifier: Programming Language :: Python :: 3.7
Classifier: Topic :: Software Development :: Libraries :: Python Modules
Requires-Python: ~=3.6
Requires-Dist: bs4
Requires-Dist: joblib
Requires-Dist: pandas
Requires-Dist: disk
Requires-Dist: lxml
Requires-Dist: slytherin
Requires-Dist: txt
